dimo/__init__.py
dimo/constants.py
dimo/dimo.py
dimo/environments.py
dimo/errors.py
dimo/eth_signer.py
dimo/permission_decoder.py
dimo/request.py
dimo/api/__init__.py
dimo/api/attestation.py
dimo/api/auth.py
dimo/api/device_definitions.py
dimo/api/token_exchange.py
dimo/api/trips.py
dimo/api/valuations.py
dimo/graphql/__init__.py
dimo/graphql/identity.py
dimo/graphql/telemetry.py
dimo_python_sdk_ng-2.0.2.dist-info/licenses/LICENSE
dimo_python_sdk_ng-2.0.2.dist-info/METADATA
dimo_python_sdk_ng-2.0.2.dist-info/WHEEL
dimo_python_sdk_ng-2.0.2.dist-info/top_level.txt
dimo_python_sdk_ng-2.0.2.dist-info/RECORD
