Metadata-Version: 2.4
Name: dimo-python-sdk-ng
Version: 2.0.2
Summary: DIMO SDK in Python
Author-email: ardevd <ardevd@protonmail.com>
Project-URL: Homepage, https://github.com/ardevd/dimo-python-sdk
Project-URL: Issues, https://github.com/ardevd/dimo-python-sdk/issues
Keywords: dimo,sdk,python,depin,web3
Classifier: Programming Language :: Python :: 3
Classifier: License :: OSI Approved :: Apache Software License
Classifier: Operating System :: OS Independent
Requires-Python: >=3.8
License-File: LICENSE
Requires-Dist: requests>=2.30.0
Requires-Dist: eth-account==0.13.4
Requires-Dist: eth-utils>=5.0.0
Dynamic: license-file
